comrp/__init__.py
comrp-0.0.0.dist-info/LICENSE
comrp-0.0.0.dist-info/METADATA
comrp-0.0.0.dist-info/WHEEL
comrp-0.0.0.dist-info/top_level.txt
comrp-0.0.0.dist-info/RECORD
